bijx/__init__.py
bijx/_version.py
bijx/cg.py
bijx/distributions.py
bijx/flowjax.py
bijx/fourier.py
bijx/lie.py
bijx/mcmc.py
bijx/samplers.py
bijx/solvers.py
bijx/utils.py
bijx/bijections/__init__.py
bijx/bijections/analytic.py
bijx/bijections/base.py
bijx/bijections/continuous.py
bijx/bijections/conv_cnf.py
bijx/bijections/coupling.py
bijx/bijections/fourier.py
bijx/bijections/meta.py
bijx/bijections/radial.py
bijx/bijections/scalar.py
bijx/bijections/splines.py
bijx/lattice/__init__.py
bijx/lattice/gauge.py
bijx/lattice/general.py
bijx/lattice/scalar.py
bijx/nn/__init__.py
bijx/nn/conv.py
bijx/nn/embeddings.py
bijx/nn/features.py
bijx/nn/nets.py
bijx-1.2.0.dist-info/licenses/LICENSE
bijx-1.2.0.dist-info/METADATA
bijx-1.2.0.dist-info/WHEEL
bijx-1.2.0.dist-info/top_level.txt
bijx-1.2.0.dist-info/RECORD
