Metadata-Version: 2.4
Name: bijx
Version: 1.2.0
Summary: Bijections & normalizing flows with JAX/NNX
Author-email: Mathis Gerdes <mathisgerdes@gmail.com>
License-Expression: Apache-2.0
Classifier: Development Status :: 4 - Beta
Classifier: Intended Audience :: Science/Research
Classifier: Programming Language :: Python :: 3
Classifier: Programming Language :: Python :: 3.10
Classifier: Programming Language :: Python :: 3.11
Classifier: Programming Language :: Python :: 3.12
Requires-Python: >=3.10
License-File: LICENSE
Requires-Dist: chex>=0.1.89
Requires-Dist: diffrax>=0.6.2
Requires-Dist: einops>=0.8.0
Requires-Dist: flax>=0.12.1
Requires-Dist: jax>=0.5
Requires-Dist: jaxlib>=0.5
Requires-Dist: jax-autovmap>=0.3.0
Requires-Dist: numpy>=2.0.2
Requires-Dist: optax>=0.2.4
Provides-Extra: dev
Requires-Dist: mypy>=1.0.0; extra == "dev"
Requires-Dist: black>=23.0.0; extra == "dev"
Requires-Dist: isort>=5.12.0; extra == "dev"
Requires-Dist: ruff>=0.0.241; extra == "dev"
Requires-Dist: pre-commit>=3.0.0; extra == "dev"
Requires-Dist: pytest>=7.0; extra == "dev"
Requires-Dist: pytest-xdist>=3.0.0; extra == "dev"
Requires-Dist: pytest-cov>=4.0.0; extra == "dev"
Requires-Dist: flowjax>=0.3.0; extra == "dev"
Requires-Dist: hypothesis[numpy]>=6.90; extra == "dev"
Requires-Dist: matplotlib>=3.9.0; extra == "dev"
Requires-Dist: nb-clean>=4.0.1; extra == "dev"
Provides-Extra: docs
Requires-Dist: sphinx; extra == "docs"
Requires-Dist: furo; extra == "docs"
Requires-Dist: myst-nb; extra == "docs"
Requires-Dist: sphinx-autodoc-typehints; extra == "docs"
Requires-Dist: sphinx-copybutton; extra == "docs"
Requires-Dist: sphinx-math-dollar; extra == "docs"
Requires-Dist: numpydoc; extra == "docs"
Requires-Dist: ipykernel; extra == "docs"
Requires-Dist: ipywidgets; extra == "docs"
Requires-Dist: matplotlib; extra == "docs"
Requires-Dist: numpy; extra == "docs"
Dynamic: license-file
